vvadlrs3/__init__.py
vvadlrs3/bestFaceEndToEnd.h5
vvadlrs3/bestLipEndToEnd.h5
vvadlrs3/convert_samples.py
vvadlrs3/dataSet.py
vvadlrs3/dlibmodels.py
vvadlrs3/faceFeatureModel.h5
vvadlrs3/lipFeatureModel.h5
vvadlrs3/onCluster.py
vvadlrs3/pretrained_models.py
vvadlrs3/sample.py
vvadlrs3/tests.py
vvadlrs3/utils/__init__.py
vvadlrs3/utils/downloadUtils.py
vvadlrs3/utils/imageUtils.py
vvadlrs3/utils/kerasUtils.py
vvadlrs3/utils/multiprocessingUtils.py
vvadlrs3/utils/plotUtils.py
vvadlrs3/utils/timeUtils.py
vvadlrs3/utils/videoUtils.py
vvadlrs3-0.2.0.dist-info/LICENSE
vvadlrs3-0.2.0.dist-info/METADATA
vvadlrs3-0.2.0.dist-info/WHEEL
vvadlrs3-0.2.0.dist-info/top_level.txt
vvadlrs3-0.2.0.dist-info/RECORD
